setup.py
messenger_server_apr_kinder.egg-info/PKG-INFO
messenger_server_apr_kinder.egg-info/SOURCES.txt
messenger_server_apr_kinder.egg-info/dependency_links.txt
messenger_server_apr_kinder.egg-info/requires.txt
messenger_server_apr_kinder.egg-info/top_level.txt
server/__init__.py
server/descryptors.py
server/metaclasses.py
server/server.py
server/server_database.py
server/server_gui.py
server/common/__init__.py
server/common/decos.py
server/common/utils.py
server/common/variables.py
server/logs/__init__.py
server/logs/config_client_log.py
server/logs/config_server_log.py